MyCryptoKeys/__init__.py
MyCryptoKeys/__main__.py
MyCryptoKeys/testServices.py
MyCryptoKeys-0.1.0.dist-info/LICENSE
MyCryptoKeys-0.1.0.dist-info/METADATA
MyCryptoKeys-0.1.0.dist-info/WHEEL
MyCryptoKeys-0.1.0.dist-info/entry_points.txt
MyCryptoKeys-0.1.0.dist-info/top_level.txt
MyCryptoKeys-0.1.0.dist-info/RECORD
