Metadata-Version: 2.1
Name: MyCryptoKeys
Version: 0.1.0
Summary: A Python MyCryptoKeys
Home-page: UNKNOWN
Author: alvaroperis
Author-email: UNKNOWN
License: UNKNOWN
Platform: UNKNOWN
